Metadata-Version: 2.1
Name: func_adl_servicex_xaodr24
Version: 1.1.4.24.2.6
Summary: func-adl typed datasets for Servicex for xAOD R24 24.2.6
Author: Gordon Watts
Author-email: gwatts@uw.edu
Requires-Python: >=3.7
Classifier: Programming Language :: Python :: 3
Classifier: Programming Language :: Python :: 3.7
Classifier: Programming Language :: Python :: 3.8
Classifier: Programming Language :: Python :: 3.9
Classifier: Programming Language :: Python :: 3.10
Classifier: Programming Language :: Python :: 3.11
Requires-Dist: func_adl_servicex (>=2.0-beta.1,<3.0)
